odoo/addons/l10n_es_auto_reload_banks/__init__.py
odoo/addons/l10n_es_auto_reload_banks/__manifest__.py
odoo/addons/l10n_es_auto_reload_banks/data/company.xml
odoo/addons/l10n_es_auto_reload_banks/models/__init__.py
odoo/addons/l10n_es_auto_reload_banks/models/ir_model_data.py
odoo12_addon_l10n_es_auto_reload_banks-12.0.1.0.0.dist-info/METADATA
odoo12_addon_l10n_es_auto_reload_banks-12.0.1.0.0.dist-info/WHEEL
odoo12_addon_l10n_es_auto_reload_banks-12.0.1.0.0.dist-info/top_level.txt
odoo12_addon_l10n_es_auto_reload_banks-12.0.1.0.0.dist-info/RECORD
