Metadata-Version: 2.1
Name: odoo12-addon-l10n-es-auto-reload-banks
Version: 12.0.1.0.0
Summary: Auto reload Spanish banks from BdE in module upgrade
Home-page: https://coopdevs.org
Author: Coopdevs Treball SCCL
License: AGPL-3
Platform: UNKNOWN
Classifier: Programming Language :: Python
Classifier: Framework :: Odoo
Classifier: License :: OSI Approved :: GNU Affero General Public License v3
Requires-Python: >=3.5
Requires-Dist: odoo12-addon-l10n-es-partner
Requires-Dist: odoo (<12.1dev,>=12.0a)
